kanbanflow2wekan/__init__.py
kanbanflow2wekan/kanbanflow.py
kanbanflow2wekan/wekan.py
kanbanflow2wekan-0.2.3.dist-info/WHEEL
kanbanflow2wekan-0.2.3.dist-info/METADATA
kanbanflow2wekan-0.2.3.dist-info/RECORD
