Metadata-Version: 2.1
Name: kanbanflow2wekan
Version: 0.2.3
Summary: This is a library to perform kanban migration from Kanbanflow to Wekan in an automated way.
Home-page: https://github.com/mdiniz97/kanbanflow2wekan
Keywords: kanbanflow2wekan,kanbanflow,wekan
Author: mdiniz97
Author-email: marcosdinizpaulo@gmail.com
Requires-Python: >=3.8,<4.0
Classifier: Programming Language :: Python
Classifier: Programming Language :: Python :: 3
Classifier: Programming Language :: Python :: 3.8
Classifier: Topic :: Software Development :: Libraries :: Python Modules
Requires-Dist: requests (>=2.25.1,<3.0.0)
Project-URL: Repository, https://github.com/mdiniz97/kanbanflow2wekan
